awsipinventory/__init__.py
awsipinventory/__main__.py
awsipinventory/templates/inventory.html
awsipinventory-0.6.3.dist-info/entry_points.txt
awsipinventory-0.6.3.dist-info/WHEEL
awsipinventory-0.6.3.dist-info/METADATA
awsipinventory-0.6.3.dist-info/RECORD
