Metadata-Version: 2.1
Name: awsipinventory
Version: 0.6.3
Summary: Tool to generate an inventory of all IP addresses in use in an account, one or multiple VPC, or one or multiple subnet.
Home-page: https://github.com/okelet/awsipinventory
Author: Juan A. S.
Author-email: okelet@gmail.com
Requires-Python: >=3.10,<4.0
Classifier: Programming Language :: Python :: 3
Classifier: Programming Language :: Python :: 3.10
Requires-Dist: Jinja2 (>=3.1.1,<4.0.0)
Requires-Dist: PyYAML (>=6.0,<7.0)
Requires-Dist: boto3 (>=1.22.0,<2.0.0)
Requires-Dist: tabulate (>=0.8.9,<0.9.0)
Project-URL: Documentation, https://github.com/okelet/awsipinventory
Project-URL: Repository, https://github.com/okelet/awsipinventory
